{"header":[["FPTO11","CWTO","EST5EDT","regulier",2021,1,5,1600,0,"prochaine_prevision",2021,1,5,2030,30]],
 "names-en":["Shelburne - Mansfield - Northern Dufferin County"],
 "names-fr":["Shelburne - Mansfield - comté de Dufferin nord"],
 "regions":[["r1115b"]],
 "ciel":[[0,4,10,10,9],
         [4,7,9,9,9],
         [7,47,10,10,9],
         [47,66,7,7,4],
         [66,69,4,4,4],
         [69,120,0,0],
         [120,228,6,6,9],
         [228,240,9,9,9]],
 "climat_temp":[[5,11,"min",-11.0],
                [11,21,"max",-3.0],
                [21,35,"min",-11.0],
                [35,45,"max",-3.0],
                [45,59,"min",-11.0],
                [59,69,"max",-3.0],
                [69,83,"min",-11.0],
                [83,93,"max",-3.0],
                [93,107,"min",-11.0],
                [107,117,"max",-3.0],
                [117,131,"min",-11.0],
                [131,141,"max",-3.0],
                [141,155,"min",-11.0],
                [155,165,"max",-3.0],
                [165,179,"min",-12.0],
                [179,189,"max",-3.0],
                [189,203,"min",-12.0],
                [203,213,"max",-3.0],
                [213,227,"min",-12.0],
                [227,237,"max",-3.0],
                [237,251,"min",-12.0]],
 "indice_qa":[[5,6,2.3],
              [6,7,2.2],
              [7,8,2.1],
              [8,9,2.0],
              [9,10,2.0],
              [10,11,2.0],
              [11,12,1.9],
              [12,13,2.0],
              [13,14,2.0],
              [14,15,2.0],
              [15,16,2.0],
              [16,17,2.0],
              [17,18,2.1],
              [18,19,2.1],
              [19,20,2.1],
              [20,21,2.1],
              [21,22,2.1],
              [22,23,2.2],
              [23,24,2.2],
              [24,25,2.1],
              [25,26,2.1],
              [26,27,2.0],
              [27,28,2.0],
              [28,29,2.1],
              [29,30,2.1],
              [30,31,2.0],
              [31,32,2.0],
              [32,33,1.9],
              [33,34,1.9],
              [34,35,1.8],
              [35,36,1.8],
              [36,37,1.8],
              [37,38,1.8],
              [38,39,1.9],
              [39,40,1.8],
              [40,41,1.8],
              [41,42,1.8],
              [42,43,1.8],
              [43,44,1.8],
              [44,45,1.8],
              [45,46,1.8],
              [46,47,1.8],
              [47,48,1.8],
              [48,49,1.7],
              [49,50,1.7],
              [50,51,1.6],
              [51,52,1.6],
              [52,53,1.6],
              [53,54,1.5],
              [54,55,1.5],
              [55,56,1.5],
              [56,57,1.5],
              [57,58,1.5],
              [58,59,1.6],
              [59,60,1.6],
              [60,61,1.6],
              [61,62,1.6],
              [62,63,1.6],
              [63,64,1.6],
              [64,65,1.5],
              [65,66,1.5],
              [66,67,1.5],
              [67,68,1.5],
              [68,69,1.6],
              [69,70,1.6],
              [70,71,1.6],
              [71,72,1.6]],
 "indice_uv":[[16,18,1.1],
              [40,42,1.1],
              [64,66,1.1],
              [88,90,1.2]],
 "pcpn":[[5,
          27,
          "possible",
          "exact",
          "averses_neige",
          "nil",
          "bref",
          [10,15,"risque","exact","bruine_verglacante","nil","bref"],
          [25,27,"risque","exact","bruine_verglacante","nil","bref"]],
         [27,
          39,
          "risque",
          "exact",
          "bruine_verglacante",
          "nil",
          "bref",
          [37,39,"possible","exact","averses_neige","nil","bref"]],
         [39,47,"possible","exact","averses_neige","nil","bref"],
         [168,204,"possible","debut_fin","averses_neige","nil","frequent"],
         [210,240,"possible","debut_fin","averses_neige","nil","frequent"]],
 "pol_O3":[[5,6,31],
           [6,9,32],
           [9,12,29],
           [12,15,25],
           [15,18,31],
           [18,21,37],
           [21,24,35],
           [24,27,31],
           [27,30,33],
           [30,33,30],
           [33,36,31],
           [36,39,34],
           [39,42,34],
           [42,45,34],
           [45,47,33],
           [47,48,33],
           [48,51,29],
           [51,54,27],
           [54,57,28],
           [57,60,28],
           [60,63,28],
           [63,66,29],
           [66,69,30],
           [69,72,30]],
 "prob":[["seuil",
          0.2,
          [0,5,0],
          [5,47,30],
          [47,120,0],
          [120,132,10],
          [132,138,0],
          [138,144,10],
          [144,150,20],
          [150,162,10],
          [162,168,20],
          [168,174,30],
          [174,180,40],
          [180,204,30],
          [204,210,20],
          [210,216,30],
          [216,240,40]]],
 "rosee":[[0,1,"point_intermediaire",-4],
          [1,2,"point_intermediaire",-4],
          [2,3,"point_intermediaire",-5],
          [3,4,"point_intermediaire",-5],
          [4,5,"point_intermediaire",-5],
          [5,6,"point_intermediaire",-6],
          [6,9,"point_intermediaire",-6],
          [9,12,"point_intermediaire",-6],
          [12,15,"point_intermediaire",-5],
          [15,18,"point_intermediaire",-5],
          [18,21,"point_intermediaire",-5],
          [21,24,"point_intermediaire",-5],
          [24,27,"point_intermediaire",-5],
          [27,30,"point_intermediaire",-7],
          [30,33,"point_intermediaire",-6],
          [33,36,"point_intermediaire",-7],
          [36,39,"point_intermediaire",-7],
          [39,42,"point_intermediaire",-6],
          [42,45,"point_intermediaire",-5],
          [45,47,"point_intermediaire",-5],
          [47,48,"point_intermediaire",-5],
          [48,51,"point_intermediaire",-5],
          [51,54,"point_intermediaire",-7],
          [54,57,"point_intermediaire",-6],
          [57,60,"point_intermediaire",-7],
          [60,63,"point_intermediaire",-8],
          [63,66,"point_intermediaire",-8],
          [66,69,"point_intermediaire",-8],
          [69,72,"point_intermediaire",-9],
          [72,75,"point_intermediaire",-10],
          [75,78,"point_intermediaire",-13],
          [78,81,"point_intermediaire",-14],
          [81,84,"point_intermediaire",-16],
          [84,87,"point_intermediaire",-15],
          [87,90,"point_intermediaire",-14],
          [90,93,"point_intermediaire",-12],
          [93,96,"point_intermediaire",-12],
          [96,99,"point_intermediaire",-15],
          [99,102,"point_intermediaire",-17],
          [102,105,"point_intermediaire",-18],
          [105,108,"point_intermediaire",-17],
          [108,111,"point_intermediaire",-17],
          [111,114,"point_intermediaire",-14],
          [114,117,"point_intermediaire",-11],
          [117,120,"point_intermediaire",-12],
          [120,123,"point_intermediaire",-14],
          [123,126,"point_intermediaire",-16],
          [126,129,"point_intermediaire",-16],
          [129,132,"point_intermediaire",-15],
          [132,135,"point_intermediaire",-12],
          [135,138,"point_intermediaire",-9],
          [138,141,"point_intermediaire",-8],
          [141,144,"point_intermediaire",-11],
          [144,147,"point_intermediaire",-12],
          [147,150,"point_intermediaire",-12],
          [150,153,"point_intermediaire",-12],
          [153,156,"point_intermediaire",-12],
          [156,159,"point_intermediaire",-9],
          [159,162,"point_intermediaire",-7],
          [162,165,"point_intermediaire",-6],
          [165,168,"point_intermediaire",-8],
          [168,171,"point_intermediaire",-9],
          [171,174,"point_intermediaire",-8],
          [174,177,"point_intermediaire",-8],
          [177,180,"point_intermediaire",-8],
          [180,183,"point_intermediaire",-8],
          [183,186,"point_intermediaire",-6],
          [186,189,"point_intermediaire",-6],
          [189,192,"point_intermediaire",-8],
          [192,195,"point_intermediaire",-8],
          [195,198,"point_intermediaire",-8],
          [198,201,"point_intermediaire",-10],
          [201,204,"point_intermediaire",-10],
          [204,207,"point_intermediaire",-8],
          [207,210,"point_intermediaire",-6],
          [210,213,"point_intermediaire",-6],
          [213,216,"point_intermediaire",-7],
          [216,219,"point_intermediaire",-8],
          [219,222,"point_intermediaire",-8],
          [222,225,"point_intermediaire",-8],
          [225,228,"point_intermediaire",-8],
          [228,231,"point_intermediaire",-6],
          [231,234,"point_intermediaire",-6],
          [234,237,"point_intermediaire",-6],
          [237,240,"point_intermediaire",-7]],
 "temp":[[0,1,"point_intermediaire",-3],
         [1,2,"point_intermediaire",-3],
         [2,3,"point_intermediaire",-3],
         [3,4,"point_intermediaire",-3],
         [4,5,"point_intermediaire",-3],
         [5,6,"point_intermediaire",-3],
         [6,9,"point_intermediaire",-4],
         [9,12,"min",-4],
         [12,15,"point_intermediaire",-3],
         [15,18,"point_intermediaire",-1],
         [18,21,"point_intermediaire",-1],
         [21,24,"stationnaire",-2],
         [24,27,"point_intermediaire",-3],
         [27,30,"point_intermediaire",-5],
         [30,33,"point_intermediaire",-4],
         [33,36,"stationnaire",-4],
         [36,39,"point_intermediaire",-3],
         [39,42,"point_intermediaire",-2],
         [42,45,"point_intermediaire",-2],
         [45,47,"stationnaire",-3],
         [47,48,"stationnaire",-2],
         [48,51,"point_intermediaire",-2],
         [51,54,"point_intermediaire",-4],
         [54,57,"point_intermediaire",-5],
         [57,60,"min",-5],
         [60,63,"point_intermediaire",-3],
         [63,66,"point_intermediaire",-3],
         [66,69,"stationnaire",-3],
         [69,72,"point_intermediaire",-5],
         [72,75,"point_intermediaire",-6],
         [75,78,"point_intermediaire",-8],
         [78,81,"point_intermediaire",-9],
         [81,84,"min",-11],
         [84,87,"point_intermediaire",-9],
         [87,90,"point_intermediaire",-5],
         [90,93,"max",-4],
         [93,96,"point_intermediaire",-6],
         [96,99,"point_intermediaire",-7],
         [99,102,"point_intermediaire",-10],
         [102,105,"point_intermediaire",-10],
         [105,108,"min",-12],
         [108,111,"point_intermediaire",-8],
         [111,114,"point_intermediaire",-4],
         [114,117,"max",-4],
         [117,120,"point_intermediaire",-5],
         [120,123,"point_intermediaire",-8],
         [123,126,"point_intermediaire",-9],
         [126,129,"point_intermediaire",-9],
         [129,132,"min",-9],
         [132,135,"point_intermediaire",-7],
         [135,138,"point_intermediaire",-3],
         [138,141,"max",-3],
         [141,144,"point_intermediaire",-5],
         [144,147,"point_intermediaire",-7],
         [147,150,"point_intermediaire",-8],
         [150,153,"point_intermediaire",-8],
         [153,156,"min",-8],
         [156,159,"point_intermediaire",-5],
         [159,162,"max",-2],
         [162,165,"point_intermediaire",-3],
         [165,168,"point_intermediaire",-4],
         [168,171,"point_intermediaire",-5],
         [171,174,"point_intermediaire",-6],
         [174,177,"point_intermediaire",-6],
         [177,180,"min",-6],
         [180,183,"point_intermediaire",-5],
         [183,186,"point_intermediaire",-3],
         [186,189,"point_intermediaire",-3],
         [189,192,"stationnaire",-4],
         [192,195,"point_intermediaire",-5],
         [195,198,"stationnaire",-6],
         [198,201,"point_intermediaire",-7],
         [201,204,"point_intermediaire",-7],
         [204,207,"point_intermediaire",-6],
         [207,210,"point_intermediaire",-3],
         [210,213,"max",-3],
         [213,216,"point_intermediaire",-4],
         [216,219,"point_intermediaire",-5],
         [219,222,"point_intermediaire",-6],
         [222,225,"point_intermediaire",-6],
         [225,228,"stationnaire",-6],
         [228,231,"point_intermediaire",-5],
         [231,234,"point_intermediaire",-3],
         [234,237,"point_intermediaire",-3],
         [237,240,"stationnaire",-4]],
 "vents":[[0,3,"sw","vitesse",10],
          [3,32,"nil","vitesse",5],
          [32,47,"n","vitesse",20],
          [47,48,"n","vitesse",10],
          [48,51,"n","vitesse",15],
          [51,78,"n","vitesse",10],
          [78,84,"nil","vitesse",5],
          [84,117,"n","vitesse",10],
          [117,126,"nw","vitesse",10],
          [126,138,"nil","vitesse",5],
          [138,144,"nw","vitesse",10],
          [144,150,"w","vitesse",10],
          [150,180,"sw","vitesse",10],
          [180,207,"w","vitesse",10],
          [207,234,"w","vitesse",15],
          [234,237,"w","vitesse",20],
          [237,240,"sw","vitesse",15]],
 "visib":[[7,14,"bancs_brouillard","continu"]],
 "en":"Shelburne - Mansfield - Northern Dufferin County.\nToday..Cloudy with 30 percent chance of flurries. Wind up to 15 km/h.\n Temperature steady near minus 2. Wind chill near minus 4.\nTonight..Cloudy. 30 percent chance of flurries this evening. Risk of\n freezing drizzle this evening and overnight. Wind becoming north\n 20 km/h overnight. Temperature steady near minus 4. Wind chill\n minus 11 overnight.\nWednesday..Cloudy with 30 percent chance of flurries. Risk of\n freezing drizzle in the morning. Wind north 20 km/h. Temperature\n steady near minus 3. Wind chill near minus 10.",
 "fr":"Shelburne - Mansfield - comté de Dufferin nord.\nAujourd'hui..Nuageux avec 30 pour cent de probabilité d'averses de\n neige. Vents jusqu'à 15 km/h. Températures stables près de moins 2.\n Refroidissement éolien près de moins 4.\nCe soir et cette nuit..Nuageux. 30 pour cent de probabilité d'averses\n de neige ce soir. Risque de bruine verglaçante ce soir et au cours\n de la nuit. Vents devenant du nord à 20 km/h au cours de la nuit.\n Températures stables près de moins 4. Refroidissement éolien\n moins 11 au cours de la nuit.\nMercredi..Nuageux avec 30 pour cent de probabilité d'averses de\n neige. Risque de bruine verglaçante le matin. Vents du nord de\n 20 km/h. Températures stables près de moins 3. Refroidissement\n éolien près de moins 10."}
